liltorch/__init__.py
liltorch/nn/__init__.py
liltorch/nn/activation.py
liltorch/nn/fully_connected.py
liltorch/nn/layer.py
liltorch/nn/loss.py
liltorch/nn/network.py
tests/__init__.py
tests/nn/__init__.py
tests/nn/test_fully_connected.py
liltorch-0.0.2.dist-info/LICENSE
liltorch-0.0.2.dist-info/METADATA
liltorch-0.0.2.dist-info/WHEEL
liltorch-0.0.2.dist-info/top_level.txt
liltorch-0.0.2.dist-info/RECORD
