Metadata-Version: 2.1
Name: liltorch
Version: 0.0.2
Summary: Small neural network library made with numpy and raw python
Author: Mateus Souza
License-File: LICENSE
Requires-Dist: numpy
